MANIFEST.in
setup.py
ate_sammy/LICENSE.txt
ate_sammy/README.md
ate_sammy/__init__.py
ate_sammy/sammy.py
ate_sammy/coding/AutoScriptGenerator.py
ate_sammy/coding/BaseGenerator.py
ate_sammy/coding/BaseTestGenerator.py
ate_sammy/coding/ProgramGenerator.py
ate_sammy/coding/ProperGenerator.py
ate_sammy/coding/TargetGenerator.py
ate_sammy/coding/TestRunnerMainGenerator.py
ate_sammy/coding/__init__.py
ate_sammy/coding/generator_utils.py
ate_sammy/coding/generators.py
ate_sammy/coding/utils.py
ate_sammy/coding/standard_tests/__init__.py
ate_sammy/coding/standard_tests/Contact/Contact.py
ate_sammy/coding/standard_tests/Contact/__init__.py
ate_sammy/coding/standard_tests/IDD/IDD.py
ate_sammy/coding/standard_tests/IDD/__init__.py
ate_sammy/coding/standard_tests/IDDq/IDDq.py
ate_sammy/coding/standard_tests/IDDq/__init__.py
ate_sammy/coding/standard_tests/IIH/IIH.py
ate_sammy/coding/standard_tests/IIH/__init__.py
ate_sammy/coding/standard_tests/IIL/IIL.py
ate_sammy/coding/standard_tests/IIL/__init__.py
ate_sammy/coding/standard_tests/IOH/IOH.py
ate_sammy/coding/standard_tests/IOH/__init__.py
ate_sammy/coding/standard_tests/IOHMAX/IOHMAX.py
ate_sammy/coding/standard_tests/IOHMAX/__init__.py
ate_sammy/coding/standard_tests/IOL/IOL.py
ate_sammy/coding/standard_tests/IOL/__init__.py
ate_sammy/coding/standard_tests/IOLMAX/IOLMAX.py
ate_sammy/coding/standard_tests/IOLMAX/__init__.py
ate_sammy/coding/standard_tests/IOS/IOS.py
ate_sammy/coding/standard_tests/IOS/__init__.py
ate_sammy/coding/standard_tests/IOZ/IOZ.py
ate_sammy/coding/standard_tests/IOZ/__init__.py
ate_sammy/coding/standard_tests/IOZH/IOZH.py
ate_sammy/coding/standard_tests/IOZH/__init__.py
ate_sammy/coding/standard_tests/IOZL/IOZL.py
ate_sammy/coding/standard_tests/IOZL/__init__.py
ate_sammy/coding/standard_tests/TDR/TDR.py
ate_sammy/coding/standard_tests/TDR/__init__.py
ate_sammy/coding/standard_tests/UID/UID.py
ate_sammy/coding/standard_tests/UID/UID.ui
ate_sammy/coding/standard_tests/UID/__init__.py
semi_ate_sammy.egg-info/PKG-INFO
semi_ate_sammy.egg-info/SOURCES.txt
semi_ate_sammy.egg-info/dependency_links.txt
semi_ate_sammy.egg-info/entry_points.txt
semi_ate_sammy.egg-info/requires.txt
semi_ate_sammy.egg-info/top_level.txt